LICENSE
README.md
pyproject.toml
setup.py
scrapeops_scrapy/__init__.py
scrapeops_scrapy/exceptions.py
scrapeops_scrapy/extension.py
scrapeops_scrapy.egg-info/PKG-INFO
scrapeops_scrapy.egg-info/SOURCES.txt
scrapeops_scrapy.egg-info/dependency_links.txt
scrapeops_scrapy.egg-info/requires.txt
scrapeops_scrapy.egg-info/top_level.txt
scrapeops_scrapy/core/__init__.py
scrapeops_scrapy/core/api.py
scrapeops_scrapy/core/controllers.py
scrapeops_scrapy/core/core.py
scrapeops_scrapy/core/error_logger.py
scrapeops_scrapy/core/model.py
scrapeops_scrapy/core/setup.py
scrapeops_scrapy/middleware/__init__.py
scrapeops_scrapy/middleware/retry.py
scrapeops_scrapy/middleware/stats.py
scrapeops_scrapy/normalizer/__init__.py
scrapeops_scrapy/normalizer/domains.py
scrapeops_scrapy/normalizer/exceptions.py
scrapeops_scrapy/normalizer/middleware.py
scrapeops_scrapy/normalizer/proxies.py
scrapeops_scrapy/normalizer/proxy_port_normalizer.py
scrapeops_scrapy/normalizer/request_response.py
scrapeops_scrapy/signals/__init__.py
scrapeops_scrapy/signals/scrapeops_signals.py
scrapeops_scrapy/signals/triggers.py
scrapeops_scrapy/stats/__init__.py
scrapeops_scrapy/stats/failed_urls.py
scrapeops_scrapy/stats/logger.py
scrapeops_scrapy/stats/model.py
scrapeops_scrapy/tests/__init__.py
scrapeops_scrapy/tests/core.py
scrapeops_scrapy/utils/__init__.py
scrapeops_scrapy/utils/error_handling.py
scrapeops_scrapy/utils/utils.py
scrapeops_scrapy/validators/__init__.py
scrapeops_scrapy/validators/item_validator.py
scrapeops_scrapy/validators/response_validator.py