Metadata-Version: 1.2
Name: scrapeops-scrapy
Version: 0.3.7
Summary: Scrapeops Scrapy SDK, is a monitoring tool for your Scrapy spiders.
Home-page: https://github.com/ScrapeOps/scrapeops-scrapy-sdk
Author: ScrapeOps
Author-email: info@scrapeops.io
License: BSD
Platform: UNKNOWN
Classifier: Programming Language :: Python
Classifier: Programming Language :: Python :: 3
Classifier: Programming Language :: Python :: 3.6
Classifier: Programming Language :: Python :: 3.7
Classifier: Programming Language :: Python :: 3.8
Classifier: Programming Language :: Python :: 3.9
Classifier: Programming Language :: Python :: 3.10
Classifier: License :: OSI Approved :: BSD License
Classifier: Operating System :: OS Independent
Classifier: Intended Audience :: Developers
Requires-Python: >=3.6
